square_commons/__init__.py
square_commons/api_utils.py
square_commons/config_reader.py
square_commons/email.py
square_commons-3.1.0.dist-info/WHEEL
square_commons-3.1.0.dist-info/METADATA
square_commons-3.1.0.dist-info/RECORD
